[
    {
        "sector": "AI 新貴 (100/2513/3317)",
        "symbol": "2513.HK",
        "name": "智譜 AI",
        "flow": "流向計算中",
        "vol": "N/A",
        "price": 1961.0,
        "lego": [
            "gray",
            "gray",
            "gray",
            "gray",
            "gray"
        ],
        "pattern": "觀察中",
        "change": "-4.15%",
        "update": "2026-06-29 10:58"
    },
    {
        "sector": "AI 新貴 (100/2513/3317)",
        "symbol": "3317.HK",
        "name": "迅策科技",
        "flow": "流向計算中",
        "vol": "N/A",
        "price": 119.4,
        "lego": [
            "blue",
            "blue",
            "blue",
            "blue",
            "gray"
        ],
        "pattern": "觀察中",
        "change": "15.92%",
        "update": "2026-06-29 10:58"
    },
    {
        "sector": "科技龍頭與平台",
        "symbol": "1810.HK",
        "name": "",
        "flow": "流向計算中",
        "vol": "N/A",
        "price": 21.86,
        "lego": [
            "blue",
            "gray",
            "gray",
            "blue",
            "gray"
        ],
        "pattern": "🦴 骨頭洗盤",
        "change": "2.05%",
        "update": "2026-06-29 10:58"
    },
    {
        "sector": "科技龍頭與平台",
        "symbol": "3690.HK",
        "name": "",
        "flow": "流向計算中",
        "vol": "N/A",
        "price": 67.65,
        "lego": [
            "gray",
            "blue",
            "blue",
            "blue",
            "gray"
        ],
        "pattern": "🦴 骨頭洗盤",
        "change": "5.29%",
        "update": "2026-06-29 10:58"
    },
    {
        "sector": "科技龍頭與平台",
        "symbol": "0700.HK",
        "name": "",
        "flow": "流向計算中",
        "vol": "N/A",
        "price": 420.2,
        "lego": [
            "blue",
            "gray",
            "gray",
            "blue",
            "gray"
        ],
        "pattern": "🦴 骨頭洗盤",
        "change": "2.04%",
        "update": "2026-06-29 10:58"
    },
    {
        "sector": "科技龍頭與平台",
        "symbol": "9988.HK",
        "name": "",
        "flow": "流向計算中",
        "vol": "N/A",
        "price": 93.0,
        "lego": [
            "blue",
            "gray",
            "blue",
            "blue",
            "gray"
        ],
        "pattern": "🦴 骨頭洗盤",
        "change": "3.91%",
        "update": "2026-06-29 10:58"
    },
    {
        "sector": "汽車與鋰電板塊",
        "symbol": "1211.HK",
        "name": "",
        "flow": "流向計算中",
        "vol": "N/A",
        "price": 72.9,
        "lego": [
            "blue",
            "gray",
            "gray",
            "blue",
            "gray"
        ],
        "pattern": "🦴 骨頭洗盤",
        "change": "0.34%",
        "update": "2026-06-29 10:58"
    },
    {
        "sector": "汽車與鋰電板塊",
        "symbol": "1772.HK",
        "name": "",
        "flow": "流向計算中",
        "vol": "N/A",
        "price": 49.28,
        "lego": [
            "gray",
            "gray",
            "blue",
            "blue",
            "gray"
        ],
        "pattern": "🦴 骨頭洗盤",
        "change": "0.78%",
        "update": "2026-06-29 10:58"
    },
    {
        "sector": "汽車與鋰電板塊",
        "symbol": "2015.HK",
        "name": "",
        "flow": "流向計算中",
        "vol": "N/A",
        "price": 45.9,
        "lego": [
            "blue",
            "gray",
            "blue",
            "blue",
            "gray"
        ],
        "pattern": "觀察中",
        "change": "-0.82%",
        "update": "2026-06-29 10:58"
    },
    {
        "sector": "新能源與電力",
        "symbol": "3393.HK",
        "name": "",
        "flow": "流向計算中",
        "vol": "N/A",
        "price": 19.54,
        "lego": [
            "gray",
            "gray",
            "gray",
            "gray",
            "gray"
        ],
        "pattern": "觀察中",
        "change": "-2.79%",
        "update": "2026-06-29 10:58"
    },
    {
        "sector": "新能源與電力",
        "symbol": "2208.HK",
        "name": "",
        "flow": "流向計算中",
        "vol": "N/A",
        "price": 9.75,
        "lego": [
            "gray",
            "blue",
            "blue",
            "gray",
            "gray"
        ],
        "pattern": "觀察中",
        "change": "-1.91%",
        "update": "2026-06-29 10:58"
    },
    {
        "sector": "黃金與商品避險",
        "symbol": "2840.HK",
        "name": "",
        "flow": "流向計算中",
        "vol": "N/A",
        "price": 2922.0,
        "lego": [
            "blue",
            "blue",
            "blue",
            "gray",
            "gray"
        ],
        "pattern": "觀察中",
        "change": "0.93%",
        "update": "2026-06-29 10:58"
    },
    {
        "sector": "黃金與商品避險",
        "symbol": "GC=F",
        "name": "",
        "flow": "N/A",
        "vol": "N/A",
        "price": 4049.5,
        "lego": [
            "blue",
            "blue",
            "gray",
            "gray",
            "gray"
        ],
        "pattern": "觀察中",
        "change": "-0.72%",
        "update": "2026-06-29 10:58"
    }
]